pyno_logger/__init__.py
pyno_logger/pyno_logger.py
pyno_logger-0.0.10.dist-info/LICENSE
pyno_logger-0.0.10.dist-info/METADATA
pyno_logger-0.0.10.dist-info/WHEEL
pyno_logger-0.0.10.dist-info/top_level.txt
pyno_logger-0.0.10.dist-info/RECORD
