Metadata-Version: 2.1
Name: pyno-logger
Version: 0.0.10
Summary: A JSON logger for Python, inspired by Pino.
Author-email: Ben Miner <ben@getampt.com>
Project-URL: Homepage, https://github.com/benminer/pyno-logger
Project-URL: Bug Tracker, https://github.com/benminer/pyno-logger/issues
Classifier: Programming Language :: Python :: 3
Classifier: License :: OSI Approved :: MIT License
Classifier: Operating System :: OS Independent
Requires-Python: >=3.6
License-File: LICENSE
